asciinema_clip/__init__.py
asciinema_clip/clipper.py
asciinema_clip-0.1.3.data/scripts/asciinema-clip
asciinema_clip-0.1.3.dist-info/METADATA
asciinema_clip-0.1.3.dist-info/WHEEL
asciinema_clip-0.1.3.dist-info/top_level.txt
asciinema_clip-0.1.3.dist-info/RECORD
