Metadata-Version: 2.1
Name: asciinema-clip
Version: 0.1.3
Summary: Clip the displaying delay on asciicast produced by asciinema
Home-page: UNKNOWN
Author: Aria Ghora Prabono
Author-email: hello@ghora.net
License: MIT
Platform: UNKNOWN
